{"_id":{"$oid":"62b19fc31cfba6a78775ff0e"},"clients":"PureIt","keyword":"Water purifier with hot and cold","time":"2022-06-21 16:08:51","product_order":[{"product_asin":"B09NSYNSJ4","product_rank":1,"sponsored":false},{"product_asin":"B0755JMLFV","product_rank":2,"sponsored":false},{"product_asin":"B0755JMF9G","product_rank":3,"sponsored":false},{"product_asin":"B00ZCL1XLW","product_rank":4,"sponsored":false},{"product_asin":"B0755D9T1M","product_rank":5,"sponsored":false},{"product_asin":"B07YWLSXQ6","product_rank":6,"sponsored":false},{"product_asin":"B07Q1J1JX5","product_rank":7,"sponsored":false},{"product_asin":"B08X4TGTTP","product_rank":8,"sponsored":false},{"product_asin":"B09XJ6MX8T","product_rank":9,"sponsored":false},{"product_asin":"B08FBZD1G5","product_rank":10,"sponsored":false},{"product_asin":"B08HWXFRKK","product_rank":11,"sponsored":false},{"product_asin":"B09F2FW4ZK","product_rank":12,"sponsored":false},{"product_asin":"B089D9SHPY","product_rank":13,"sponsored":false},{"product_asin":"B09574TLHG","product_rank":14,"sponsored":false},{"product_asin":"B0755JMLFV","product_rank":15,"sponsored":false},{"product_asin":"B09BCYZC8Z","product_rank":16,"sponsored":false},{"product_asin":"B0859RHH6X","product_rank":17,"sponsored":false},{"product_asin":"B08KFC9HR6","product_rank":18,"sponsored":false},{"product_asin":"B09YNXYR9B","product_rank":19,"sponsored":false},{"product_asin":"B08KHPDG3N","product_rank":20,"sponsored":false},{"product_asin":"B09NKS8Q2V","product_rank":21,"sponsored":false},{"product_asin":"B0755D9T1M","product_rank":22,"sponsored":false}]}
{"_id":{"$oid":"62b19fc41cfba6a78775ff53"},"clients":"PureIt","keyword":"Water purifier uv uf only","time":"2022-06-21 16:08:51","product_order":[{"product_asin":"B01HXUJB2W","product_rank":1,"sponsored":false},{"product_asin":"B008LN6156","product_rank":2,"sponsored":false},{"product_asin":"B08KHPDG3N","product_rank":3,"sponsored":false},{"product_asin":"B008LN6156","product_rank":4,"sponsored":false},{"product_asin":"B09VS25ZX7","product_rank":5,"sponsored":false},{"product_asin":"B08FYVXWYB","product_rank":6,"sponsored":false},{"product_asin":"B09XK3QJZ6","product_rank":7,"sponsored":false},{"product_asin":"B08CSG8TC3","product_rank":8,"sponsored":false},{"product_asin":"B01HXUJB2W","product_rank":9,"sponsored":false},{"product_asin":"B07YLPRK72","product_rank":10,"sponsored":false},{"product_asin":"B08BJN4MP3","product_rank":11,"sponsored":false},{"product_asin":"B09HC2F3FY","product_rank":12,"sponsored":false},{"product_asin":"B07TL45M93","product_rank":13,"sponsored":false},{"product_asin":"B0859RHH6X","product_rank":14,"sponsored":false},{"product_asin":"B07NYQS8JF","product_rank":15,"sponsored":false},{"product_asin":"B09XK64CNH","product_rank":16,"sponsored":false},{"product_asin":"B0755JMF9G","product_rank":17,"sponsored":false},{"product_asin":"B08Y5NGWVY","product_rank":18,"sponsored":false},{"product_asin":"B0859R9BLN","product_rank":19,"sponsored":false},{"product_asin":"B09NW4LQCK","product_rank":20,"sponsored":false},{"product_asin":"B09NKS8Q2V","product_rank":21,"sponsored":false},{"product_asin":"B08KFRFSP9","product_rank":22,"sponsored":false}]}
{"_id":{"$oid":"62b19fc41cfba6a78775ff96"},"clients":"PureIt","keyword":"Water purifier","time":"2022-06-21 16:08:51","product_order":[{"product_asin":"B09TB2YC13","product_rank":1,"sponsored":false},{"product_asin":"B08BJN4MP3","product_rank":2,"sponsored":false},{"product_asin":"B07YC8JHMB","product_rank":3,"sponsored":false},{"product_asin":"B07FJNNZCJ","product_rank":4,"sponsored":false},{"product_asin":"B09X1P3J6G","product_rank":5,"sponsored":false},{"product_asin":"B009DA69W6","product_rank":6,"sponsored":false},{"product_asin":"B07SQX4GHH","product_rank":7,"sponsored":false},{"product_asin":"B0095S9JU0","product_rank":8,"sponsored":false},{"product_asin":"B09K7BNP2R","product_rank":9,"sponsored":false},{"product_asin":"B09YY5BP26","product_rank":10,"sponsored":false},{"product_asin":"B09NKS8Q2V","product_rank":11,"sponsored":false},{"product_asin":"B09NQ1K1D9","product_rank":12,"sponsored":false},{"product_asin":"B08KHPDG3N","product_rank":13,"sponsored":false},{"product_asin":"B08HWXFRKK","product_rank":14,"sponsored":false},{"product_asin":"B07MQ5X54S","product_rank":15,"sponsored":false},{"product_asin":"B07D3R62MH","product_rank":16,"sponsored":false},{"product_asin":"B09SFCSCVY","product_rank":17,"sponsored":false},{"product_asin":"B08BJN4MP3","product_rank":18,"sponsored":false},{"product_asin":"B094YD54TC","product_rank":19,"sponsored":false},{"product_asin":"B0B26PNYHS","product_rank":20,"sponsored":false},{"product_asin":"B08KHPDG3N","product_rank":21,"sponsored":false},{"product_asin":"B08KFRFSP9","product_rank":22,"sponsored":false}]}
{"_id":{"$oid":"62b19fc81cfba6a78775ffdb"},"clients":"PureIt","keyword":"Water purifier Pureit","time":"2022-06-21 16:08:51","product_order":[{"product_asin":"B08BJN4MP3","product_rank":1,"sponsored":false},{"product_asin":"B09M45XKKF","product_rank":2,"sponsored":false},{"product_asin":"B094YD54TC","product_rank":3,"sponsored":false},{"product_asin":"B08B27R8MP","product_rank":4,"sponsored":false},{"product_asin":"B08BJN4MP3","product_rank":5,"sponsored":false},{"product_asin":"B009PJ8Y3W","product_rank":6,"sponsored":false},{"product_asin":"B01N6CA6H6","product_rank":7,"sponsored":false},{"product_asin":"B09M45XKKF","product_rank":8,"sponsored":false},{"product_asin":"B07MWBVTLP","product_rank":9,"sponsored":false},{"product_asin":"B00I8QV2VY","product_rank":10,"sponsored":false},{"product_asin":"B08B27R8MP","product_rank":11,"sponsored":false},{"product_asin":"B00I8QV2VY","product_rank":12,"sponsored":false},{"product_asin":"B07SFZ21BW","product_rank":13,"sponsored":false},{"product_asin":"B07GDQWSZ9","product_rank":14,"sponsored":false},{"product_asin":"B0785FD8LP","product_rank":15,"sponsored":false},{"product_asin":"B08MFP6FJC","product_rank":16,"sponsored":false},{"product_asin":"B01MYH9UZL","product_rank":17,"sponsored":false},{"product_asin":"B07FDZ9KL7","product_rank":18,"sponsored":false},{"product_asin":"B00W0YWAKC","product_rank":19,"sponsored":false},{"product_asin":"B096XHHTVC","product_rank":20,"sponsored":false},{"product_asin":"B096XHHTVC","product_rank":21,"sponsored":false},{"product_asin":"B07MWBVTLP","product_rank":22,"sponsored":false}]}
{"_id":{"$oid":"62b19fcc1cfba6a787760024"},"clients":"PureIt","keyword":"Water purifier ro","time":"2022-06-21 16:08:51","product_order":[{"product_asin":"B09TB2YC13","product_rank":1,"sponsored":false},{"product_asin":"B08BJN4MP3","product_rank":2,"sponsored":false},{"product_asin":"B07YC8JHMB","product_rank":3,"sponsored":false},{"product_asin":"B07MQ5X54S","product_rank":4,"sponsored":false},{"product_asin":"B07SQX4GHH","product_rank":5,"sponsored":false},{"product_asin":"B07FJNNZCJ","product_rank":6,"sponsored":false},{"product_asin":"B09SFCSCVY","product_rank":7,"sponsored":false},{"product_asin":"B01JLRXIQK","product_rank":8,"sponsored":false},{"product_asin":"B094YD54TC","product_rank":9,"sponsored":false},{"product_asin":"B09K7BNP2R","product_rank":10,"sponsored":false},{"product_asin":"B0B24Q8K4M","product_rank":11,"sponsored":false},{"product_asin":"B08KHPDG3N","product_rank":12,"sponsored":false},{"product_asin":"B07MWBVTLP","product_rank":13,"sponsored":false},{"product_asin":"B08B27R8MP","product_rank":14,"sponsored":false},{"product_asin":"B07DYSX1HP","product_rank":15,"sponsored":false},{"product_asin":"B08BJN4MP3","product_rank":16,"sponsored":false},{"product_asin":"B09CGQ6FCK","product_rank":17,"sponsored":false},{"product_asin":"B08BPLRWNS","product_rank":18,"sponsored":false},{"product_asin":"B08JZH6RCK","product_rank":19,"sponsored":false},{"product_asin":"B09YY5BP26","product_rank":20,"sponsored":false},{"product_asin":"B09NKS8Q2V","product_rank":21,"sponsored":false},{"product_asin":"B09HC2KN1V","product_rank":22,"sponsored":false}]}
{"_id":{"$oid":"62b19fd01cfba6a787760075"},"clients":"PureIt","keyword":"Water purifier ro uv uf tds","time":"2022-06-21 16:08:51","product_order":[{"product_asin":"B08BJN4MP3","product_rank":1,"sponsored":false},{"product_asin":"B09YLWT89W","product_rank":2,"sponsored":false},{"product_asin":"B09X1P3J6G","product_rank":3,"sponsored":false},{"product_asin":"B0859RHH6X","product_rank":4,"sponsored":false},{"product_asin":"B0859R9BLN","product_rank":5,"sponsored":false},{"product_asin":"B08KHPDG3N","product_rank":6,"sponsored":false},{"product_asin":"B09MVPMWCF","product_rank":7,"sponsored":false},{"product_asin":"B096NTB9XT","product_rank":8,"sponsored":false},{"product_asin":"B07MZ9YDJ6","product_rank":9,"sponsored":false},{"product_asin":"B09G9TB7D9","product_rank":10,"sponsored":false},{"product_asin":"B08KHPDG3N","product_rank":11,"sponsored":false},{"product_asin":"B09HC2F3FY","product_rank":12,"sponsored":false},{"product_asin":"B07MQ5X54S","product_rank":13,"sponsored":false},{"product_asin":"B09MCXCDPT","product_rank":14,"sponsored":false},{"product_asin":"B08BPQM5TQ","product_rank":15,"sponsored":false},{"product_asin":"B08JZH6RCK","product_rank":16,"sponsored":false},{"product_asin":"B08KJ6FGBL","product_rank":17,"sponsored":false},{"product_asin":"B09YY5BP26","product_rank":18,"sponsored":false},{"product_asin":"B09Z317N2J","product_rank":19,"sponsored":false},{"product_asin":"B09CGQ6FCK","product_rank":20,"sponsored":false},{"product_asin":"B09NKS8Q2V","product_rank":21,"sponsored":false},{"product_asin":"B07MQ5X54S","product_rank":22,"sponsored":false}]}
